LouisTools/HTMLTestRunner_py3.py
LouisTools/__init__.py
LouisTools/louis_consts.py
LouisTools/louis_datetime.py
LouisTools/louis_decorators.py
LouisTools/louis_df.py
LouisTools/louis_email.py
LouisTools/louis_finance.py
LouisTools/louis_io.py
LouisTools/louis_keyrings.py
LouisTools/louis_log.py
LouisTools/louis_os.py
LouisTools/louis_re.py
LouisTools-0.2.0.dist-info/LICENSE
LouisTools-0.2.0.dist-info/METADATA
LouisTools-0.2.0.dist-info/WHEEL
LouisTools-0.2.0.dist-info/top_level.txt
LouisTools-0.2.0.dist-info/RECORD
